CHANGELOG.md
CHANGELOG.rst
MANIFEST.in
README.md
README.rst
requirements.txt
setup.py
buffalofq/__init__.py
buffalofq/_version.py
buffalofq/bfq_auditor.py
buffalofq/bfq_buffguts.py
buffalofq.egg-info/PKG-INFO
buffalofq.egg-info/SOURCES.txt
buffalofq.egg-info/dependency_links.txt
buffalofq.egg-info/requires.txt
buffalofq.egg-info/top_level.txt
scripts/buffalofq_mover