Metadata-Version: 1.1
Name: buffalofq
Version: 0.0.2
Summary: File movement utility
Home-page: http://github.com/kenfar/buffalofq
Author: Ken Farmer
Author-email: kenfar@gmail.com
License: BSD
Keywords: data management file utility
Platform: UNKNOWN
Classifier: Programming Language :: Python :: 2.7
Classifier: Programming Language :: Python :: Implementation :: CPython
Classifier: Programming Language :: Python :: Implementation :: PyPy
